memmap_replay_buffer/__init__.py
memmap_replay_buffer/episode_collector.py
memmap_replay_buffer/replay_buffer.py
memmap_replay_buffer/replay_buffer_h5py.py
memmap_replay_buffer-0.0.27.dist-info/METADATA
memmap_replay_buffer-0.0.27.dist-info/WHEEL
memmap_replay_buffer-0.0.27.dist-info/licenses/LICENSE
memmap_replay_buffer-0.0.27.dist-info/RECORD
