Metadata-Version: 2.4
Name: memmap-replay-buffer
Version: 0.0.27
Summary: Simple Replay Buffer for RL
Project-URL: Homepage, https://pypi.org/project/memmap-replay-buffer/
Project-URL: Repository, https://github.com/lucidrains/memmap-replay-buffer
Author-email: Phil Wang <lucidrains@gmail.com>
License: MIT License
License-File: LICENSE
Keywords: artificial intelligence,deep learning,replay buffer
Classifier: Development Status :: 4 - Beta
Classifier: Intended Audience :: Developers
Classifier: License :: OSI Approved :: MIT License
Classifier: Programming Language :: Python :: 3.9
Classifier: Topic :: Scientific/Engineering :: Artificial Intelligence
Requires-Python: >=3.9
Requires-Dist: beartype
Requires-Dist: einops>=0.8.1
Requires-Dist: einx>=0.3.0
Requires-Dist: numpy
Requires-Dist: torch>=2.4
Provides-Extra: examples
Provides-Extra: test
Requires-Dist: h5py; extra == 'test'
Requires-Dist: pytest; extra == 'test'
